git_clone_group/__init__.py
git_clone_group/__main__.py
git_clone_group/__version__.py
git_clone_group/cli.py
git_clone_group/config.py
git_clone_group/exceptions.py
git_clone_group/git_operations.py
git_clone_group/gitlab_client.py
git_clone_group/group_processor.py
git_clone_group/main.py
git_clone_group/session.py
git_clone_group/git_clone_group/__init__.py
git_clone_group/git_clone_group/__main__.py
git_clone_group/git_clone_group/__version__.py
git_clone_group/git_clone_group/cli.py
git_clone_group/git_clone_group/config.py
git_clone_group/git_clone_group/exceptions.py
git_clone_group/git_clone_group/git_operations.py
git_clone_group/git_clone_group/gitlab_client.py
git_clone_group/git_clone_group/group_processor.py
git_clone_group/git_clone_group/main.py
git_clone_group/git_clone_group/session.py
git_clone_group/pyarmor_runtime_000000/__init__.py
git_clone_group/pyarmor_runtime_000000/pyarmor_runtime.so
git_clone_group-1.2.5.dist-info/licenses/LICENSE
git_clone_group-1.2.5.dist-info/METADATA
git_clone_group-1.2.5.dist-info/WHEEL
git_clone_group-1.2.5.dist-info/entry_points.txt
git_clone_group-1.2.5.dist-info/top_level.txt
git_clone_group-1.2.5.dist-info/RECORD
