Metadata-Version: 2.4
Name: git-clone-group
Version: 1.2.5
Summary: Clone or update all projects from a GitLab group and its subgroups
Home-page: https://github.com/bpzhang/git_clone_group
Author: bp zhang
Author-email: zbp1024@gmail.com
License: Proprietary
Classifier: Development Status :: 4 - Beta
Classifier: Intended Audience :: Developers
Classifier: Topic :: Software Development :: Version Control :: Git
Classifier: Programming Language :: Python :: 3
Classifier: Programming Language :: Python :: 3.7
Classifier: Programming Language :: Python :: 3.8
Classifier: Programming Language :: Python :: 3.9
Classifier: Programming Language :: Python :: 3.10
Classifier: Programming Language :: Python :: 3.11
Classifier: Programming Language :: Python :: 3.12
Requires-Python: >=3.7.0
License-File: LICENSE
Requires-Dist: requests>=2.28.0
Requires-Dist: tqdm>=4.65.0
Requires-Dist: aiohttp>=3.8.0
Dynamic: author
Dynamic: author-email
Dynamic: classifier
Dynamic: description
Dynamic: description-content-type
Dynamic: home-page
Dynamic: license
Dynamic: license-file
Dynamic: requires-dist
Dynamic: requires-python
Dynamic: summary
